qtensor/CircuitComposer.py
qtensor/DebugFrameworks.py
qtensor/FeynmanSimulator.py
qtensor/MergedSimulator.py
qtensor/OpFactory.py
qtensor/ProcessingFrameworks.py
qtensor/QAOASimulator.py
qtensor/Simulate.py
qtensor/__init__.py
qtensor/cli.py
qtensor/exatn_framework.py
qtensor/toolbox.py
qtensor/utils.py
qtensor/contraction_backends/__init__.py
qtensor/contraction_backends/base_class.py
qtensor/contraction_backends/cupy.py
qtensor/contraction_backends/mkl.py
qtensor/contraction_backends/numpy.py
qtensor/contraction_backends/opt_einsum.py
qtensor/contraction_backends/performance_measurement_decorator.py
qtensor/contraction_backends/torch.py
qtensor/contraction_backends/transposed.py
qtensor/contraction_backends/tests/__init__.py
qtensor/contraction_backends/tests/test_cupy.py
qtensor/contraction_backends/tests/test_mkl.py
qtensor/contraction_backends/tests/test_torch.py
qtensor/merged_indices/__init__.py
qtensor/merged_indices/bucket_elimination.py
qtensor/optimisation/Greedy.py
qtensor/optimisation/Optimizer.py
qtensor/optimisation/RGreedy.py
qtensor/optimisation/TensorNet.py
qtensor/optimisation/__init__.py
qtensor/optimisation/late_parallelisation.py
qtensor/optimisation/networkit/__init__.py
qtensor/optimisation/networkit/greedy_networkit.py
qtensor/parameter_optimization/__init__.py
qtensor/parameter_optimization/base_optimizer.py
qtensor/parameter_optimization/torch_optimizer.py
qtensor/parameter_optimization/proceduces/__init__.py
qtensor/parameter_optimization/proceduces/torch.py
qtensor/problems/__init__.py
qtensor/problems/energy_expectation.py
qtensor/problems/test_expectation.py
qtensor/simplify_circuit/__init__.py
qtensor/simplify_circuit/gates.py
qtensor/simplify_circuit/simplify_circuit.py
qtensor/simplify_circuit/simplify_circuit_api.py
qtensor/tests/__init__.py
qtensor/tests/qaoa_quimb.py
qtensor/tests/qiskit_qaoa_energy.py
qtensor/tests/test_bucket_backends.py
qtensor/tests/test_composers.py
qtensor/tests/test_lightcone_orbits.py
qtensor-0.1.2.dist-info/LICENSE
qtensor-0.1.2.dist-info/METADATA
qtensor-0.1.2.dist-info/WHEEL
qtensor-0.1.2.dist-info/top_level.txt
qtensor-0.1.2.dist-info/RECORD
